picoraster/__init__.py
picoraster/band.py
picoraster/geotransform.py
picoraster/instruction.py
picoraster/part.py
picoraster/pipeline.py
picoraster/source.py
picoraster/types.py
picoraster-0.0.2.dist-info/LICENCE
picoraster-0.0.2.dist-info/METADATA
picoraster-0.0.2.dist-info/WHEEL
picoraster-0.0.2.dist-info/top_level.txt
picoraster-0.0.2.dist-info/RECORD
