Metadata-Version: 2.1
Name: picoraster
Version: 0.0.2
Summary: Lazy raster band processing
Home-page: UNKNOWN
Author: Nat Wilson
Author-email: natw@fortyninemaps.com
License: UNKNOWN
Platform: UNKNOWN
Classifier: Programming Language :: Python :: 3
Classifier: License :: OSI Approved :: MIT License
Classifier: Operating System :: OS Independent
Classifier: Topic :: Scientific/Engineering :: GIS
Requires-Python: >3.3
Requires-Dist: numpy (>=1.1)
Requires-Dist: GDAL (>=2.0)
